exchange_radar/__init__.py
exchange_radar/consumer/__init__.py
exchange_radar/consumer/main.py
exchange_radar/consumer/settings/__init__.py
exchange_radar/consumer/settings/base.py
exchange_radar/consumer/tests/__init__.py
exchange_radar/consumer/tests/conftest.py
exchange_radar/consumer/tests/test_main.py
exchange_radar/producer/__init__.py
exchange_radar/producer/enums.py
exchange_radar/producer/main.py
exchange_radar/producer/models.py
exchange_radar/producer/publisher.py
exchange_radar/producer/serializers/__init__.py
exchange_radar/producer/serializers/base.py
exchange_radar/producer/serializers/binance.py
exchange_radar/producer/serializers/bitstamp.py
exchange_radar/producer/serializers/bybit.py
exchange_radar/producer/serializers/coinbase.py
exchange_radar/producer/serializers/htx.py
exchange_radar/producer/serializers/kraken.py
exchange_radar/producer/serializers/kucoin.py
exchange_radar/producer/serializers/mexc.py
exchange_radar/producer/serializers/okx.py
exchange_radar/producer/settings/__init__.py
exchange_radar/producer/settings/base.py
exchange_radar/producer/settings/exchanges.py
exchange_radar/producer/settings/routing_keys.py
exchange_radar/producer/tasks/__init__.py
exchange_radar/producer/tasks/base.py
exchange_radar/producer/tasks/binance.py
exchange_radar/producer/tasks/bitstamp.py
exchange_radar/producer/tasks/bybit.py
exchange_radar/producer/tasks/coinbase.py
exchange_radar/producer/tasks/htx.py
exchange_radar/producer/tasks/kraken.py
exchange_radar/producer/tasks/kucoin.py
exchange_radar/producer/tasks/libs/__init__.py
exchange_radar/producer/tasks/libs/kraken.py
exchange_radar/producer/tasks/mexc.py
exchange_radar/producer/tasks/okx.py
exchange_radar/producer/tests/__init__.py
exchange_radar/producer/tests/test_serializers.py
exchange_radar/producer/tests/test_utils.py
exchange_radar/producer/utils.py
exchange_radar/scheduler/__init__.py
exchange_radar/scheduler/alerts/__init__.py
exchange_radar/scheduler/alerts/market_sentiment.py
exchange_radar-1.8.0.dist-info/LICENSE
exchange_radar-1.8.0.dist-info/METADATA
exchange_radar-1.8.0.dist-info/WHEEL
exchange_radar-1.8.0.dist-info/entry_points.txt
exchange_radar-1.8.0.dist-info/RECORD
