Metadata-Version: 2.3
Name: exchange-radar
Version: 1.8.0
Summary: Live trading information from various cryptocurrency exchanges.
License: GNU GPLv3
Keywords: cryptocurrency,bitcoin,btc,ethereum,eth,chainlink,link,trading,crypto exchanges,exchange,crypto,binance,coinbase,kraken,kucoin,okx,bybit,bitstamp,mexc,htx
Author: Paulo Antunes
Author-email: pjmlantunes@gmail.com
Requires-Python: >=3.12,<4.0
Classifier: Development Status :: 5 - Production/Stable
Classifier: Intended Audience :: Developers
Classifier: Intended Audience :: Financial and Insurance Industry
Classifier: License :: OSI Approved :: GNU General Public License v3 (GPLv3)
Classifier: License :: Other/Proprietary License
Classifier: Natural Language :: English
Classifier: Operating System :: OS Independent
Classifier: Programming Language :: Python :: 3
Classifier: Programming Language :: Python :: 3.12
Classifier: Programming Language :: Python :: 3.13
Classifier: Topic :: Software Development :: Libraries :: Python Modules
Requires-Dist: click (>=8.1.5,<9.0.0)
Requires-Dist: copra (>=1.2.9,<2.0.0)
Requires-Dist: environs (>=11.0.0,<12.0.0)
Requires-Dist: huey (>=2.5.0,<3.0.0)
Requires-Dist: jinja2 (>=3.1.2,<4.0.0)
Requires-Dist: pika (>=1.3.2,<2.0.0)
Requires-Dist: pybit (>=5.6.2,<6.0.0)
Requires-Dist: pydantic (>=2.0,<3.0)
Requires-Dist: pymexc (>=1.2.0,<2.0.0)
Requires-Dist: python-binance (>=1.0.17,<2.0.0)
Requires-Dist: python-kucoin (>=2.1.3,<3.0.0)
Requires-Dist: python-okx (>=0.2.6,<0.3.0)
Requires-Dist: python-telegram-bot (>=21.1.1,<22.0.0)
Requires-Dist: redis-om (>=0.2.1,<0.3.0)
Requires-Dist: requests (>=2.31.0,<3.0.0)
Requires-Dist: starlette (>=0.37.2,<0.38.0)
Requires-Dist: types-requests (==2.31.0.0)
Requires-Dist: urllib3 (>=1.26.16,<2.0.0)
Requires-Dist: uvicorn[standard] (>=0.22.0,<0.23.0)
Project-URL: Homepage, https://exchangeradar.tech
Project-URL: Repository, https://github.com/pantunes/exchange-radar
